feature_check/__init__.py
feature_check/__main__.py
feature_check/defs.py
feature_check/expr.py
feature_check/obtain.py
feature_check/parser.py
feature_check/py.typed
feature_check/version.py
feature_check-2.3.1.dist-info/METADATA
feature_check-2.3.1.dist-info/WHEEL
feature_check-2.3.1.dist-info/entry_points.txt
feature_check-2.3.1.dist-info/RECORD
