Metadata-Version: 2.4
Name: feature_check
Version: 2.3.1
Summary: Query a program for supported features
Project-URL: Homepage, https://devel.ringlet.net/misc/feature-check/
Project-URL: Changelog, https://gitlab.com/ppentchev/feature-check/-/blob/master/docs/changes.md
Project-URL: Repository, https://gitlab.com/ppentchev/feature-check
Author-email: Peter Pentchev <roam@ringlet.net>
License: BSD-2-Clause
Classifier: Development Status :: 5 - Production/Stable
Classifier: Environment :: Console
Classifier: Intended Audience :: Developers
Classifier: Intended Audience :: System Administrators
Classifier: License :: DFSG approved
Classifier: License :: Freely Distributable
Classifier: License :: OSI Approved :: BSD License
Classifier: Operating System :: POSIX
Classifier: Operating System :: Unix
Classifier: Programming Language :: Python
Classifier: Programming Language :: Python :: 3
Classifier: Programming Language :: Python :: 3 :: Only
Classifier: Programming Language :: Python :: 3.10
Classifier: Programming Language :: Python :: 3.11
Classifier: Programming Language :: Python :: 3.12
Classifier: Programming Language :: Python :: 3.13
Classifier: Programming Language :: Python :: 3.14
Classifier: Topic :: Software Development :: Libraries
Classifier: Topic :: Software Development :: Libraries :: Python Modules
Classifier: Topic :: Utilities
Requires-Python: >=3.10
Requires-Dist: click<9,>=8.1.5
Requires-Dist: pyparsing<4,>=3.2
